awsmr.py
awsmr-0.1.1.dist-info/entry_points.txt
awsmr-0.1.1.dist-info/WHEEL
awsmr-0.1.1.dist-info/METADATA
awsmr-0.1.1.dist-info/RECORD
