Metadata-Version: 2.1
Name: awsmr
Version: 0.1.1
Summary: 
Author: Iain Samuel McLean Elder
Author-email: iain@isme.es
Requires-Python: >=3.8,<4.0
Classifier: Programming Language :: Python :: 3
Classifier: Programming Language :: Python :: 3.10
Classifier: Programming Language :: Python :: 3.8
Classifier: Programming Language :: Python :: 3.9
Requires-Dist: awscli (>=1.22.41,<2.0.0)
Requires-Dist: boto3 (>=1.20.41,<2.0.0)
